unity_mcp_MB/__init__.py
unity_mcp_MB/asset_tools.py
unity_mcp_MB/config.py
unity_mcp_MB/editor_tools.py
unity_mcp_MB/material_tools.py
unity_mcp_MB/object_tools.py
unity_mcp_MB/scene_tools.py
unity_mcp_MB/script_tools.py
unity_mcp_MB/server.py
unity_mcp_MB/unity_connection.py
unity_mcp_mb-0.2.4.dist-info/METADATA
unity_mcp_mb-0.2.4.dist-info/WHEEL
unity_mcp_mb-0.2.4.dist-info/entry_points.txt
unity_mcp_mb-0.2.4.dist-info/top_level.txt
unity_mcp_mb-0.2.4.dist-info/RECORD
