Metadata-Version: 2.4
Name: unity-mcp-MB
Version: 0.2.4
Summary: Unity MCP Server: A Unity package for Unity Editor integration via the Model Context Protocol (MCP).
Requires-Python: >=3.12
Requires-Dist: httpx>=0.28.1
Requires-Dist: mcp[cli]>=1.4.1
